example/__init__.py
example/bert_sub_driver.py
example/config.py
example/word_embed_sub_driver.py
lexsub/__init__.py
lexsub/config.py
lexsub/algorithms/__init__.py
lexsub/algorithms/bert_mask_lm.py
lexsub/algorithms/custom_utils.py
lexsub/algorithms/embedding_utils.py
lexsub/algorithms/wordnet_models.py
lexsub/process_data/__init__.py
lexsub/process_data/data_reader.py
lexsub/process_data/definition.py
lexsub/process_data/indexer.py
lexsub/process_data/tokenizer.py
lexsub-1.1.4.dist-info/LICENSE
lexsub-1.1.4.dist-info/METADATA
lexsub-1.1.4.dist-info/WHEEL
lexsub-1.1.4.dist-info/top_level.txt
lexsub-1.1.4.dist-info/RECORD
