Metadata-Version: 2.1
Name: lexsub
Version: 1.1.4
Summary: State of the art Lexical Substitution in Context
Home-page: https://github.com/anishacharya/LexSub
Author: Anish Acharya
Author-email: anishacharya@utexas.edu
License: UNKNOWN
Platform: UNKNOWN
Classifier: Programming Language :: Python :: 3
Classifier: License :: OSI Approved :: MIT License
Classifier: Operating System :: OS Independent
Requires-Python: >=3.6
